steganographr/__init__.py
steganographr/__main__.py
steganographr/tests/__init__.py
steganographr/tests/test.py
steganographr-1.2.0.dist-info/LICENSE
steganographr-1.2.0.dist-info/METADATA
steganographr-1.2.0.dist-info/WHEEL
steganographr-1.2.0.dist-info/entry_points.txt
steganographr-1.2.0.dist-info/top_level.txt
steganographr-1.2.0.dist-info/RECORD
