Metadata-Version: 2.1
Name: steganographr
Version: 1.2.0
Summary: Hide text in plain sight using invisible zero-width characters.
Author-email: jmcb <joelsgp@protonmail.com>
License: GNU GENERAL PUBLIC LICENSE
Project-URL: Home, https://github.com/joelsgp/steganographr-python
Classifier: Programming Language :: Python :: 3
Classifier: License :: OSI Approved :: GNU General Public License v3 (GPLv3)
Classifier: Development Status :: 4 - Beta
Classifier: Natural Language :: English
Classifier: Operating System :: OS Independent
Classifier: Topic :: Security
Requires-Python: >=3.8
License-File: LICENSE
